odoo/addons/product_main_supplierinfo/README.rst
odoo/addons/product_main_supplierinfo/__init__.py
odoo/addons/product_main_supplierinfo/__manifest__.py
odoo/addons/product_main_supplierinfo/i18n/fr.po
odoo/addons/product_main_supplierinfo/i18n/it.po
odoo/addons/product_main_supplierinfo/i18n/product_main_supplierinfo.pot
odoo/addons/product_main_supplierinfo/models/__init__.py
odoo/addons/product_main_supplierinfo/models/product_product.py
odoo/addons/product_main_supplierinfo/readme/CONTRIBUTORS.md
odoo/addons/product_main_supplierinfo/readme/CREDITS.md
odoo/addons/product_main_supplierinfo/readme/DESCRIPTION.md
odoo/addons/product_main_supplierinfo/static/description/icon.png
odoo/addons/product_main_supplierinfo/static/description/index.html
odoo/addons/product_main_supplierinfo/tests/__init__.py
odoo/addons/product_main_supplierinfo/tests/test_product_main_supplier.py
odoo/addons/product_main_supplierinfo/views/product_product.xml
odoo_addon_product_main_supplierinfo-18.0.1.0.0.4.dist-info/METADATA
odoo_addon_product_main_supplierinfo-18.0.1.0.0.4.dist-info/WHEEL
odoo_addon_product_main_supplierinfo-18.0.1.0.0.4.dist-info/top_level.txt
odoo_addon_product_main_supplierinfo-18.0.1.0.0.4.dist-info/RECORD
